CHANGES.txt
LICENSE.txt
MANIFEST.in
README.rst
setup.py
js/__init__.py
js.socketio.egg-info/PKG-INFO
js.socketio.egg-info/SOURCES.txt
js.socketio.egg-info/dependency_links.txt
js.socketio.egg-info/entry_points.txt
js.socketio.egg-info/namespace_packages.txt
js.socketio.egg-info/not-zip-safe
js.socketio.egg-info/requires.txt
js.socketio.egg-info/top_level.txt
js/socketio/__init__.py
js/socketio/test_socketio.txt
js/socketio/resources/js/socket.io.js
js/socketio/resources/js/socket.io.min.js