Metadata-Version: 1.0
Name: js.socketio
Version: 0.9.10
Summary: fanstatic socketio.
Home-page: https://github.com/RedTurtle/js.socketio
Author: RedTurtle Developers
Author-email: sviluppoplone@redturtle.it
License: BSD
Keywords: fanstatic socketio redturtle
Platform: UNKNOWN
